hlsdownload/__init__.py
hlsdownload/debug.py
hlsdownload/downloader.py
hlsdownload-0.0.16.dist-info/DESCRIPTION.rst
hlsdownload-0.0.16.dist-info/entry_points.txt
hlsdownload-0.0.16.dist-info/METADATA
hlsdownload-0.0.16.dist-info/metadata.json
hlsdownload-0.0.16.dist-info/RECORD
hlsdownload-0.0.16.dist-info/top_level.txt
hlsdownload-0.0.16.dist-info/WHEEL
