Metadata-Version: 2.0
Name: hlsdownload
Version: 0.0.16
Summary: Download HLS and convert to MP4
Home-page: https://github.com/Eyevinn/hls-downloader
Author: Jonas Birme
Author-email: jonas.birme@eyevinn.se
License: MIT
Platform: UNKNOWN
Requires-Dist: m3u8 (>=0.3.0)
Requires-Dist: pycurl
